pygentrification/__init__.py
pygentrification/api_calls.py
pygentrification/bates_freeman_indices.py
pygentrification/ding_index.py
pygentrification/folium_funcs.py
pygentrification-0.0.5.dist-info/LICENSE.txt
pygentrification-0.0.5.dist-info/METADATA
pygentrification-0.0.5.dist-info/WHEEL
pygentrification-0.0.5.dist-info/top_level.txt
pygentrification-0.0.5.dist-info/RECORD
