Metadata-Version: 2.1
Name: pygentrification
Version: 0.0.5
Summary: A python package for calculating and visualizing gentrification indices from published academic research
Author-email: Winn Costantini <wc555@drexel.edu>, Adam Thompson <adam.thompson0001@temple.edu>, Josh Scrabeck <joshua.scrabeck@temple.edu>
Project-URL: Homepage, https://github.com/joshscrabeck/pygentrification
Keywords: gentrification
Classifier: Programming Language :: Python :: 3
Classifier: License :: OSI Approved :: BSD License
Requires-Python: !=3.10,>=3.9
License-File: LICENSE.txt
Requires-Dist: requests
Requires-Dist: pandas
Requires-Dist: geopandas
Requires-Dist: tobler
Requires-Dist: numpy (==1.22.4)
Requires-Dist: folium
Requires-Dist: branca
